pyide/__init__.py
pyide/__main__.py
pyide/app.py
pyide/style.tcss
pyide/screens/__init__.py
pyide/screens/editor.py
pyide/widgets/__init__.py
pyide/widgets/code_area.py
pyide/widgets/file_tree.py
pyide-0.0.2.dist-info/METADATA
pyide-0.0.2.dist-info/WHEEL
pyide-0.0.2.dist-info/entry_points.txt
pyide-0.0.2.dist-info/RECORD
