Metadata-Version: 2.3
Name: pyide
Version: 0.0.2
Summary: The Most Pythonic IDE
Project-URL: Homepage, https://github.com/Zimzozaur/PyIDE
Project-URL: Issues, https://github.com/Zimzozaur/PyIDE/issues
Author-email: Simon Piechutowski <szymonpiechutowski@gmail.com>
Classifier: Operating System :: OS Independent
Classifier: Programming Language :: Python :: 3
Requires-Python: >=3.12
Requires-Dist: platformdirs~=4.2.2
Requires-Dist: textual>=0.83.0
Requires-Dist: textual[syntax]
Provides-Extra: dev
Requires-Dist: pre-commit~=4.0.1; extra == 'dev'
Requires-Dist: pytest-asyncio~=0.24.0; extra == 'dev'
Requires-Dist: pytest-env~=1.1.3; extra == 'dev'
Requires-Dist: pytest-mock~=3.14.0; extra == 'dev'
Requires-Dist: pytest~=8.3.2; extra == 'dev'
Requires-Dist: ruff>=0.6.1; extra == 'dev'
Requires-Dist: textual-dev~=1.5.1; extra == 'dev'
